.gitlab-ci.yml
.travis.yml
CHANGES.rst
CONTRIBUTORS.rst
DEVELOP.rst
LICENSE.GPL
LICENSE.rst
MANIFEST.in
README.rst
constraints.txt
constraints_plone43.txt
constraints_plone50.txt
constraints_plone51.txt
constraints_plone52.txt
requirements.txt
setup.cfg
setup.py
tox.ini
docs/collective.templates.pdf
docs/html/addnewtemplatecenter.html
docs/html/addnewtemplateproject.html
docs/html/configuration.html
docs/html/contacttotemplateproject.html
docs/html/genindex.html
docs/html/index.html
docs/html/installation.html
docs/html/messaging.html
docs/html/publishtemplateproject.html
docs/html/search.html
docs/html/searchindex.js
docs/html/_images/configuration_template_center_form1.png
docs/html/_images/configuration_template_center_form2.png
docs/html/_images/configuration_template_center_form3.png
docs/html/_images/create_template_center.png
docs/html/_images/create_template_project.png
docs/html/_images/install_collective_templates.png
docs/html/_images/navigation_add_templates_center.png
docs/html/_images/template_center_form1.png
docs/html/_images/template_center_form2.png
docs/html/_images/template_center_form3.png
docs/html/_images/template_center_sharing.png
docs/html/_images/template_project_form1.png
docs/html/_images/template_project_form2.png
docs/html/_images/template_project_form3.png
docs/html/_images/template_project_form4.png
docs/html/_images/template_project_form5.png
docs/html/_images/template_project_form6.png
docs/html/_sources/addnewtemplatecenter.rst.txt
docs/html/_sources/addnewtemplateproject.rst.txt
docs/html/_sources/configuration.rst.txt
docs/html/_sources/contacttotemplateproject.rst.txt
docs/html/_sources/index.rst.txt
docs/html/_sources/installation.rst.txt
docs/html/_sources/messaging.rst.txt
docs/html/_sources/publishtemplateproject.rst.txt
docs/html/_static/ajax-loader.gif
docs/html/_static/alabaster.css
docs/html/_static/basic.css
docs/html/_static/comment-bright.png
docs/html/_static/comment-close.png
docs/html/_static/comment.png
src/collective.templates.egg-info/PKG-INFO
src/collective.templates.egg-info/SOURCES.txt
src/collective.templates.egg-info/dependency_links.txt
src/collective.templates.egg-info/entry_points.txt
src/collective.templates.egg-info/namespace_packages.txt
src/collective.templates.egg-info/not-zip-safe
src/collective.templates.egg-info/requires.txt
src/collective.templates.egg-info/top_level.txt
